.gitattributes
.gitignore
LICENSE
MANIFEST.in
README.rst
plantain.jpg
setup.cfg
setup.py
versioneer.py
.eggs/README.txt
plantain/__init__.py
plantain/_version.py
plantain/main.py
plantain.egg-info/PKG-INFO
plantain.egg-info/SOURCES.txt
plantain.egg-info/dependency_links.txt
plantain.egg-info/entry_points.txt
plantain.egg-info/not-zip-safe
plantain.egg-info/pbr.json
plantain.egg-info/requires.txt
plantain.egg-info/top_level.txt