Metadata-Version: 1.1
Name: plantain
Version: 0.2.post1
Summary: Command line tool for managing Mandrill templates.
Home-page: https://github.com/clearclaw/plantain
Author: J C Lawrence
Author-email: claw@kanga.nu
License: GPL v3.0
Keywords: Mandrill templates commandline API
Platform: UNKNOWN
Classifier: Development Status :: 4 - Beta
Classifier: Intended Audience :: Developers
Classifier: License :: OSI Approved :: GNU General Public License v3 or later (GPLv3+)
Classifier: Topic :: Utilities
